onstats/__init__.py
onstats/stats.py
onstats/util.py
onstats-0.9.4.dist-info/METADATA
onstats-0.9.4.dist-info/WHEEL
onstats-0.9.4.dist-info/RECORD
