Metadata-Version: 2.1
Name: onstats
Version: 0.9.4
Summary: Online stats in python, based in generators with send
Home-page: https://github.com/PabloRuizCuevas/onstats
Author: Pablo Ruiz
Author-email: pablo.r.c@live.com
Requires-Python: >=3.9,<4.0
Classifier: Programming Language :: Python :: 3
Classifier: Programming Language :: Python :: 3.9
Classifier: Programming Language :: Python :: 3.10
Classifier: Programming Language :: Python :: 3.11
Classifier: Programming Language :: Python :: 3.12
Requires-Dist: numpy (>=1.26.4,<2.0.0)
Project-URL: Repository, https://github.com/PabloRuizCuevas/onstats
